django_login_email-0.6.3.dist-info/METADATA
django_login_email-0.6.3.dist-info/WHEEL
django_login_email-0.6.3.dist-info/entry_points.txt
django_login_email-0.6.3.dist-info/licenses/LICENSE
django_login_email/__init__.py
django_login_email/admin.py
django_login_email/apps.py
django_login_email/email.py
django_login_email/errors.py
django_login_email/forms/__init__.py
django_login_email/forms/register.py
django_login_email/iputils.py
django_login_email/management/__init__.py
django_login_email/management/commands/__init__.py
django_login_email/management/commands/list_register_record.py
django_login_email/migrations/0001_initial.py
django_login_email/migrations/0002_emaillogin_sault_emaillogin_validated_and_more.py
django_login_email/migrations/0003_rename_last_time_emaillogin_expired_time.py
django_login_email/migrations/0004_emailregister.py
django_login_email/migrations/0005_emailrecord_delete_emaillogin_delete_emailregister.py
django_login_email/migrations/0006_ipban.py
django_login_email/migrations/__init__.py
django_login_email/models.py
django_login_email/templates/login_email/base.html
django_login_email/templates/login_email/components/mail_template.html
django_login_email/templates/login_email/error.html
django_login_email/templates/login_email/home.html
django_login_email/templates/login_email/login.html
django_login_email/templates/login_email/success.html
django_login_email/token.py
django_login_email/views/__init__.py
django_login_email/views/limit.py
django_login_email/views/login.py
django_login_email/views/mixin.py
django_login_email/views/utils.py
django_login_email/wrap.py
settings/__init__.py
settings/asgi.py
settings/settings.py
settings/urls.py
settings/wsgi.py
testapp/__init__.py
testapp/admin.py
testapp/apps.py
testapp/management/__init__.py
testapp/management/commands/__init__.py
testapp/management/commands/create_user.py
testapp/management/commands/mmigrate.py
testapp/migrations/__init__.py
testapp/models.py
testapp/tests.py
testapp/urls.py
testapp/views/__init__.py
django_login_email-0.6.3.dist-info/RECORD
