Metadata-Version: 2.1
Name: django-login-email
Version: 0.6.3
Summary: A django app for login with email.
Author-Email: svtter <svtter@qq.com>
Project-URL: homepage, https://github.com/Svtter/django-login-email
Project-URL: repository, https://github.com/Svtter/django-login-email.git
Project-URL: changelog, https://github.com/Svtter/django-login-email/blob/master/CHANGELOG.md
Project-URL: bugs, https://github.com/Svtter/django-login-email/issues
Requires-Python: >=3.10
Requires-Dist: django>=5.0.4
Requires-Dist: pycryptodome>=3.20.0
